script/__init__.py
script/caseRun.py
script/irrInterfaceImplement.py
script/publicFile.py
script/studies_get.py
txInterface/__init__.py
txInterface/basic.py
txInterface/getValue.py
txInterface/htmlTestReportCN.py
txInterface/jsondiff.py
txInterface/log.py
txInterfaceTest-0.0.5.dist-info/LICENSE
txInterfaceTest-0.0.5.dist-info/METADATA
txInterfaceTest-0.0.5.dist-info/WHEEL
txInterfaceTest-0.0.5.dist-info/top_level.txt
txInterfaceTest-0.0.5.dist-info/zip-safe
txInterfaceTest-0.0.5.dist-info/RECORD
